main.py
opt.py
utils.py
SRE_Conv/__init__.py
SRE_Conv/sre_conv.py
SRE_Conv/sre_resnet.py
SRE_Conv/sre_resnet_3d.py
SRE_Conv/transforms.py
SRE_Conv/utils.py
SRE_Conv-1.0.1.dist-info/LICENSE
SRE_Conv-1.0.1.dist-info/METADATA
SRE_Conv-1.0.1.dist-info/WHEEL
SRE_Conv-1.0.1.dist-info/top_level.txt
SRE_Conv-1.0.1.dist-info/RECORD
