Metadata-Version: 2.1
Name: SRE-Conv
Version: 1.0.1
Summary: Official package for 'SRE-Conv: Symmetric Rotation Equivariant Convolution for Biomedical Image Classification'
Author-email: "Yuexi Du, Jiazhen Zhang, Tal Zeevi, Nicha C. Dvornek, John A. Onofrey" <yuexi.du@yale.edu>
Project-URL: Homepage, https://github.com/XYPB/SRE-Conv
Project-URL: Issue, https://github.com/XYPB/SRE-Conv/issues
Classifier: Programming Language :: Python :: 3
Classifier: License :: OSI Approved :: MIT License
Classifier: Operating System :: OS Independent
Requires-Python: >=3.8
License-File: LICENSE
Requires-Dist: scipy>=1.9.0
Requires-Dist: numpy>=1.22.0
Requires-Dist: torch>=1.8.0
